[
    {
        "img":"../img/zebra.png",
        "nombre":"Zebra",
        "indiceAleatorio":""
    },
    {
        "img":"../img/cat.png",
        "nombre":"Cat",
        "indiceAleatorio":""
    },
    {
        "img":"../img/giraffe.png",
        "nombre":"Giraffe",
        "indiceAleatorio":""
    },
    {
        "img":"../img/Leon.png",
        "nombre":"Leon",
        "indiceAleatorio":""
    },
    {
        "img":"../img/dog.png",
        "nombre":"Dog",
        "indiceAleatorio":""
    },
    {
        "img":"../img/cow.png",
        "nombre":"Cow",
        "indiceAleatorio":""
    }
]